almdrlib/__init__.py
almdrlib/client.py
almdrlib/config.py
almdrlib/constants.py
almdrlib/environment.py
almdrlib/exceptions.py
almdrlib/region.py
almdrlib/session.py
almdrlib/version.py
almdrlib/docs/__init__.py
almdrlib/docs/service.py
alertlogic_sdk_python-1.0.74.dist-info/AUTHORS.rst
alertlogic_sdk_python-1.0.74.dist-info/LICENSE
alertlogic_sdk_python-1.0.74.dist-info/METADATA
alertlogic_sdk_python-1.0.74.dist-info/WHEEL
alertlogic_sdk_python-1.0.74.dist-info/top_level.txt
alertlogic_sdk_python-1.0.74.dist-info/RECORD
