Metadata-Version: 2.1
Name: alertlogic-sdk-python
Version: 1.0.74
Summary: Alert Logic Software Development Kit for Python.
Home-page: https://github.com/alertlogic/alertlogic-sdk-python
Author: Alert Logic Inc.
Author-email: devsupport@alertlogic.com
License: MIT license
Keywords: alertlogic-sdk,alertlogic-sdk-python,alertlogic-mdr-sdk,almdrlib,alertlogic
Platform: any
Classifier: Development Status :: 4 - Beta
Classifier: Intended Audience :: Developers
Classifier: License :: OSI Approved :: MIT License
Classifier: Natural Language :: English
Classifier: Operating System :: MacOS :: MacOS X
Classifier: Operating System :: Microsoft :: Windows
Classifier: Operating System :: POSIX
Classifier: Programming Language :: Python :: 3.6
Classifier: Programming Language :: Python :: 3.7
Classifier: Programming Language :: Python :: 3.8
Requires-Python: >=3.6
License-File: LICENSE
License-File: AUTHORS.rst
Requires-Dist: requests (>=2.18)
Requires-Dist: configparser (>=4.0.2)
Requires-Dist: pyyaml (>=5.4.1)
Requires-Dist: jsonschema[format_nongpl] (==3.2.0)
Requires-Dist: m2r2 (==0.3.2)
Requires-Dist: boto3 (>=1.16.57)
Requires-Dist: alertlogic-sdk-definitions (>=0.1.110)
Provides-Extra: dev
Requires-Dist: pytest (>=3) ; extra == 'dev'
Requires-Dist: mock (>=2.0.0) ; extra == 'dev'
Requires-Dist: httpretty (>=0.8.14) ; extra == 'dev'
Requires-Dist: pycodestyle (>=2.3.1) ; extra == 'dev'
Requires-Dist: jsonschema[format_nongpl] (==3.2.0) ; extra == 'dev'
